{
  "file_info": {
    "filename": "970cd46149f2.jpg",
    "source_url": "https://i.pinimg.com/236x/35/ff/41/35ff4195907bd63ef117fe34f545dc35.jpg",
    "pinterest_id": "488359153363541766",
    "file_size": 2389488,
    "resolution": "2645x3080",
    "download_timestamp": "2025-09-28T16:00:00.207779"
  },
  "kolam_properties": {
    "region": "tamil_nadu",
    "style": [
      "freehand",
      "colored"
    ],
    "complexity": "simple",
    "detected_keywords": [
      "rangoli",
      "kolam",
      "padi"
    ],
    "confidence_score": 0.6000000000000001,
    "requires_manual_validation": false,
    "color_palette": [
      "#5c5359",
      "#cfd3e9",
      "#3b3235",
      "#9697af",
      "#636173"
    ],
    "visual_complexity": 0.41,
    "symmetry": {
      "horizontal": false,
      "vertical": false
    }
  },
  "pinterest_metadata": {
    "pin_url": "https://www.pinterest.com/pin/488359153363541766/",
    "description": "padikolam in 2025 | Simple rangoli, Padi kolam, Padi",
    "alt_text": "padikolam in 2025 | Simple rangoli, Padi kolam, Padi",
    "board_name": "",
    "pinner_username": "",
    "engagement": {
      "saves": 0,
      "comments": 0
    }
  },
  "classification_data": {
    "method": "keyword_matching",
    "matched_terms": [
      "kolam",
      "padi",
      "rangoli"
    ],
    "suggested_tags": [
      "tamil-nadu",
      "freehand",
      "colored"
    ]
  },
  "processing_status": {
    "downloaded": true,
    "metadata_extracted": true,
    "classified": true,
    "validated": false
  }
}