{
  "file_info": {
    "filename": "c440de5cf5ce.jpg",
    "source_url": "https://i.pinimg.com/236x/a4/7d/c2/a47dc2eb4b03c45d465e87d70972c387.jpg",
    "pinterest_id": "2955556002790703",
    "file_size": 109327,
    "resolution": "600x853",
    "download_timestamp": "2025-09-28T15:39:07.758762"
  },
  "kolam_properties": {
    "region": "karnataka",
    "style": [
      "colored"
    ],
    "complexity": "simple",
    "detected_keywords": [
      "rangoli"
    ],
    "confidence_score": 0.4,
    "requires_manual_validation": true,
    "color_palette": [
      "#000000",
      "#050b09",
      "#efefee",
      "#0c0709",
      "#05080b"
    ],
    "visual_complexity": 0.48,
    "symmetry": {
      "horizontal": true,
      "vertical": true
    }
  },
  "pinterest_metadata": {
    "pin_url": "https://www.pinterest.com/pin/2955556002790703/",
    "description": "Selva Rajesh | Very easy rangoli designs, Easy rangoli designs videos, Simple rangoli border designs",
    "alt_text": "Selva Rajesh | Very easy rangoli designs, Easy rangoli designs videos, Simple rangoli border designs",
    "board_name": "",
    "pinner_username": "",
    "engagement": {
      "saves": 0,
      "comments": 0
    }
  },
  "classification_data": {
    "method": "keyword_matching",
    "matched_terms": [
      "rangoli",
      "rangoli"
    ],
    "suggested_tags": [
      "karnataka",
      "colored"
    ]
  },
  "processing_status": {
    "downloaded": true,
    "metadata_extracted": true,
    "classified": true,
    "validated": false
  }
}