{
  "file_info": {
    "filename": "cbf01ecd1799.jpg",
    "source_url": "https://i.pinimg.com/236x/d2/db/60/d2db6097e30c42a588f44d5bd034c812.jpg",
    "pinterest_id": "669699407129526328",
    "file_size": 92740,
    "resolution": "563x507",
    "download_timestamp": "2025-09-28T15:45:07.179592"
  },
  "kolam_properties": {
    "region": "tamil_nadu",
    "style": [
      "pulli",
      "colored"
    ],
    "complexity": "simple",
    "detected_keywords": [
      "rangoli",
      "dots",
      "kolam"
    ],
    "confidence_score": 0.6000000000000001,
    "requires_manual_validation": false,
    "color_palette": [
      "#2f1f18",
      "#61534d",
      "#e9dfd9",
      "#a59a95",
      "#4c3b35"
    ],
    "visual_complexity": 0.84,
    "symmetry": {
      "horizontal": false,
      "vertical": false
    }
  },
  "pinterest_metadata": {
    "pin_url": "https://www.pinterest.com/pin/669699407129526328/",
    "description": "Easy Peacock Rangoli Design With Dots | Easy Peacock Muggulu |Simple Peacock Kolam | #PeacockRan… in 2025 | Simple flower design, Rangoli designs, Rangoli designs with dots",
    "alt_text": "Easy Peacock Rangoli Design With Dots | Easy Peacock Muggulu |Simple Peacock Kolam | #PeacockRan… in 2025 | Simple flower design, Rangoli designs, Rangoli designs with dots",
    "board_name": "",
    "pinner_username": "",
    "engagement": {
      "saves": 0,
      "comments": 0
    }
  },
  "classification_data": {
    "method": "keyword_matching",
    "matched_terms": [
      "kolam",
      "dots",
      "rangoli"
    ],
    "suggested_tags": [
      "tamil-nadu",
      "pulli",
      "colored"
    ]
  },
  "processing_status": {
    "downloaded": true,
    "metadata_extracted": true,
    "classified": true,
    "validated": false
  }
}